tests/__init__.py
tests/test_mysql.py
xrx_mysql_utils/__init__.py
xrx_mysql_utils-1.0.6.dist-info/METADATA
xrx_mysql_utils-1.0.6.dist-info/WHEEL
xrx_mysql_utils-1.0.6.dist-info/top_level.txt
xrx_mysql_utils-1.0.6.dist-info/RECORD
