Metadata-Version: 2.1
Name: xrx-mysql-utils
Version: 1.0.6
Summary: A mysql utility package
Classifier: Programming Language :: Python :: 3
Classifier: License :: OSI Approved :: MIT License
Classifier: Operating System :: OS Independent
Requires-Python: >=3.7
Requires-Dist: mysql-connector-python
Requires-Dist: python-dotenv
Requires-Dist: sentry-sdk
